octodns_netbox_dns/__about__.py
octodns_netbox_dns/__init__.py
octodns_netbox_dns-0.3.15.dist-info/METADATA
octodns_netbox_dns-0.3.15.dist-info/WHEEL
octodns_netbox_dns-0.3.15.dist-info/licenses/LICENSE
octodns_netbox_dns-0.3.15.dist-info/RECORD
