Metadata-Version: 2.4
Name: octodns-netbox-dns
Version: 0.3.15
Summary: octodns netbox-dns provider
Project-URL: Homepage, https://github.com/olofvndrhr/octodns-netbox-dns
Project-URL: History, https://github.com/olofvndrhr/octodns-netbox-dns/commits/master
Project-URL: Tracker, https://github.com/olofvndrhr/octodns-netbox-dns/issues
Project-URL: Source, https://github.com/olofvndrhr/octodns-netbox-dns
Author-email: "Jeffrey C. Ollie" <jeff@ocjtech.us>, Ivan Schaller <ivan@schaller.sh>
License-Expression: MIT
License-File: LICENSE
Classifier: Programming Language :: Python :: 3.11
Requires-Python: >=3.11
Requires-Dist: dnspython>=2.7.0
Requires-Dist: pynetbox>=7.5.0
